tmux_projector/__init__.py
tmux_projector/exceptions.py
tmux_projector/projector.py
tmux_projector/run.py
tmux_projector/utils.py
tmux_projector/validator.py
tmux_projector/models/__init__.py
tmux_projector/models/options.py
tmux_projector/models/pane.py
tmux_projector/models/session.py
tmux_projector/models/window.py
tmux_projector-0.0.5.dist-info/METADATA
tmux_projector-0.0.5.dist-info/WHEEL
tmux_projector-0.0.5.dist-info/entry_points.txt
tmux_projector-0.0.5.dist-info/top_level.txt
tmux_projector-0.0.5.dist-info/RECORD
