Metadata-Version: 2.1
Name: tmux-projector
Version: 0.0.5
Summary: Tool to start tmux projects more easily
Home-page: UNKNOWN
Author-email: avjves@gmail.com
License: UNKNOWN
Platform: UNKNOWN
Requires-Python: >=3.7
